{
  "generated": "2026-03-25T20:20:07.058488",
  "rrf_k": 60,
  "topk": 60,
  "bayesian_alpha": 0.5,
  "results": [
    {
      "dataset": "MIRACL",
      "method": "BM25",
      "n_queries": 213,
      "ndcg_at_10": 0.6385,
      "recall_at_10": 0.7974,
      "mrr": 0.6172,
      "latency_p50": 0.44,
      "latency_p95": 0.6,
      "latency_p99": 0.74
    },
    {
      "dataset": "MIRACL",
      "method": "Dense",
      "n_queries": 213,
      "ndcg_at_10": 0.7904,
      "recall_at_10": 0.913,
      "mrr": 0.801,
      "latency_p50": 1.2,
      "latency_p95": 1.58,
      "latency_p99": 1.79
    },
    {
      "dataset": "MIRACL",
      "method": "RRF",
      "n_queries": 213,
      "ndcg_at_10": 0.7683,
      "recall_at_10": 0.8932,
      "mrr": 0.7834,
      "latency_p50": 1.79,
      "latency_p95": 2.38,
      "latency_p99": 2.7
    },
    {
      "dataset": "MIRACL",
      "method": "Bayesian",
      "n_queries": 213,
      "ndcg_at_10": 0.7272,
      "recall_at_10": 0.8706,
      "mrr": 0.7218,
      "latency_p50": 9.55,
      "latency_p95": 12.76,
      "latency_p99": 14.33
    },
    {
      "dataset": "EZIS",
      "method": "BM25",
      "n_queries": 131,
      "ndcg_at_10": 0.9162,
      "recall_at_10": 0.9847,
      "mrr": 0.8936,
      "latency_p50": 0.47,
      "latency_p95": 0.53,
      "latency_p99": 0.55
    },
    {
      "dataset": "EZIS",
      "method": "Dense",
      "n_queries": 131,
      "ndcg_at_10": 0.8041,
      "recall_at_10": 0.9351,
      "mrr": 0.7624,
      "latency_p50": 0.63,
      "latency_p95": 0.75,
      "latency_p99": 0.85
    },
    {
      "dataset": "EZIS",
      "method": "RRF",
      "n_queries": 131,
      "ndcg_at_10": 0.8641,
      "recall_at_10": 0.9695,
      "mrr": 0.829,
      "latency_p50": 0.92,
      "latency_p95": 1.09,
      "latency_p99": 1.35
    },
    {
      "dataset": "EZIS",
      "method": "Bayesian",
      "n_queries": 131,
      "ndcg_at_10": 0.9249,
      "recall_at_10": 0.9847,
      "mrr": 0.9033,
      "latency_p50": 13.87,
      "latency_p95": 15.01,
      "latency_p99": 15.27
    }
  ]
}